reason_workbench_poc/__init__.py
reason_workbench_poc/main.py
reason_workbench_poc-0.1.0.dist-info/METADATA
reason_workbench_poc-0.1.0.dist-info/WHEEL
reason_workbench_poc-0.1.0.dist-info/entry_points.txt
reason_workbench_poc-0.1.0.dist-info/top_level.txt
reason_workbench_poc-0.1.0.dist-info/RECORD
