Metadata-Version: 2.1
Name: reason-workbench-poc
Version: 0.1.0
Requires-Dist: transformers
Requires-Dist: bert-score
Requires-Dist: pandas
Requires-Dist: matplotlib
